{
  "avg_actions": 6.691,
  "avg_utility_model": -1.367,
  "avg_utility_p0": -0.133,
  "checkpoint": "experiments/holdem_tuned_pot_odds_dagger_500/holdem_policy.pt",
  "equity_sims": 8,
  "folds": 462,
  "hands": 1000,
  "hands_per_model_player": 500,
  "model_player": "both",
  "opponent_policy": "pot-odds",
  "rollout_sims": null,
  "seat_metrics": [
    {
      "avg_actions": 6.64,
      "avg_utility_model": -1.5,
      "avg_utility_p0": -1.5,
      "checkpoint": "experiments/holdem_tuned_pot_odds_dagger_500/holdem_policy.pt",
      "equity_sims": 8,
      "folds": 224,
      "hands": 500,
      "model_player": 0,
      "opponent_policy": "pot-odds",
      "rollout_sims": null,
      "seed": 150,
      "showdowns": 276,
      "utility_stderr_model": 0.4356047554905846,
      "utility_stderr_p0": 0.4356047554905846,
      "utility_stdev_model": 9.740418445991219,
      "utility_stdev_p0": 9.740418445991219
    },
    {
      "avg_actions": 6.742,
      "avg_utility_model": -1.234,
      "avg_utility_p0": 1.234,
      "checkpoint": "experiments/holdem_tuned_pot_odds_dagger_500/holdem_policy.pt",
      "equity_sims": 8,
      "folds": 238,
      "hands": 500,
      "model_player": 1,
      "opponent_policy": "pot-odds",
      "rollout_sims": null,
      "seed": 150,
      "showdowns": 262,
      "utility_stderr_model": 0.4470057228184723,
      "utility_stderr_p0": 0.4470057228184723,
      "utility_stdev_model": 9.99535182553533,
      "utility_stdev_p0": 9.99535182553533
    }
  ],
  "seed": 150,
  "showdowns": 538,
  "utility_stderr_model": 0.31194810886207114,
  "utility_stderr_p0": 0.31490391467156365,
  "utility_stdev_model": 9.864665357863013,
  "utility_stdev_p0": 9.958136144654553
}
